[
  {
    "image": "img61.png",
    "annotations": [
      {
        "label": "car",
        "coordinates": {
          "x": 21.938811188811183,
          "y": 284.527972027972,
          "width": 43.877622377622366,
          "height": 41.0
        }
      },
      {
        "label": "car",
        "coordinates": {
          "x": 137.87762237762237,
          "y": 301.027972027972,
          "width": 122.00000000000001,
          "height": 54.0
        }
      },
      {
        "label": "truck",
        "coordinates": {
          "x": 443.87762237762234,
          "y": 255.027972027972,
          "width": 50.0,
          "height": 68.0
        }
      },
      {
        "label": "tuk-tuk",
        "coordinates": {
          "x": 482.37762237762234,
          "y": 264.527972027972,
          "width": 21.0,
          "height": 29.0
        }
      },
      {
        "label": "tuk-tuk",
        "coordinates": {
          "x": 510.8776223776224,
          "y": 272.027972027972,
          "width": 30.000000000000057,
          "height": 40.0
        }
      },
      {
        "label": "motorcycle",
        "coordinates": {
          "x": 554.8776223776224,
          "y": 282.527972027972,
          "width": 20.0,
          "height": 27.0
        }
      },
      {
        "label": "car",
        "coordinates": {
          "x": 737.8776223776224,
          "y": 269.027972027972,
          "width": 58.0,
          "height": 32.0
        }
      },
      {
        "label": "motorcycle",
        "coordinates": {
          "x": 940.3776223776224,
          "y": 290.527972027972,
          "width": 91.0,
          "height": 55.0
        }
      }
    ]
  }
]
